django_domains-0.6.dist-info/DESCRIPTION.rst
django_domains-0.6.dist-info/METADATA
django_domains-0.6.dist-info/RECORD
django_domains-0.6.dist-info/WHEEL
django_domains-0.6.dist-info/metadata.json
django_domains-0.6.dist-info/top_level.txt
domains/__init__.py
domains/apps.py
domains/compat.py
domains/middleware.py
domains/models.py
domains/settings.py
domains/tests.py
domains/utils.py
domains/hooks/__init__.py
domains/hooks/base.py
domains/hooks/site_id.py
domains/loaders/__init__.py
domains/loaders/app_directories.py
domains/loaders/base.py
domains/loaders/filesystem.py
domains/templates/custom_test_index.html
domains/templates/test_index.html
domains/templates/test.bar.com/test_index.html
domains/templates/test.foo.com/test_index.html
