Metadata-Version: 2.0
Name: django-domains
Version: 0.6
Summary: An application that allows you to run many different sites on one Django instance
Home-page: UNKNOWN
Author: Mikhail Porokhovnichenko
Author-email: marazmiki@gmail.com
License: UNKNOWN
Platform: UNKNOWN
Classifier: Environment :: Web Environment
Classifier: Programming Language :: Python
Classifier: Framework :: Django
Requires-Dist: Django
